{
    "version": "0.2.0",
    "configurations": [
        {
            "name": "Run vhost (example)",
            "type": "go",
            "request": "launch",
            "mode": "auto",
            "program": "$./cmd/vhost",
            "console": "integratedTerminal",
            "cwd": "${workspaceFolder}",
            "args": ["--config", "doc-example/h1.lnx"]

        },
        {
            "name": "Run vrouter (example)",
            "type": "go",
            "request": "launch",
            "mode": "auto",
            "program": "$./cmd/vrouter",
            "console": "integratedTerminal",
            "cwd": "${workspaceFolder}",
            "args": ["--config", "doc-example/r1.lnx"]
        }
    ]
}